{
  "nber": {
    "label": "NBER",
    "papers": [
      {
        "title": "Acknowledgments",
        "authors": "",
        "year": "2018",
        "doi": "10.1016/j.biopsych.2018.05.002",
        "link": "https://doi.org/10.1016/j.biopsych.2018.05.002"
      },
      {
        "title": "Who Belongs? The Determinants of Selective Membership into the National Bureau of Economic Research",
        "authors": "Kleemans, Thornton",
        "year": "2021",
        "doi": "10.1257/PANDP.20211123",
        "link": "https://doi.org/10.1257/PANDP.20211123"
      },
      {
        "title": "The National Bureau of Economic Research",
        "authors": "Moore",
        "year": "1950",
        "doi": "10.1080/00031305.1950.10501640",
        "link": "https://doi.org/10.1080/00031305.1950.10501640"
      },
      {
        "title": "Social Security Programs and Retirement around the World: Working Longer Courtney C. Coile, Kevin Milligan, and David A. Wise (Editors), National Bureau of Economic Research Conference Report, University of Chicago Press, 2019, Hardcover $130, 576 pages",
        "authors": "Yu",
        "year": "2021",
        "doi": "10.1017/S1474747221000123",
        "link": "https://doi.org/10.1017/S1474747221000123"
      },
      {
        "title": "National Bureau of Economic Research (NBER)",
        "authors": "Heath-Brown",
        "year": "2019",
        "doi": "10.1007/978-1-349-57823-8_156",
        "link": "https://doi.org/10.1007/978-1-349-57823-8_156"
      }
    ]
  },
  "jama": {
    "label": "JAMA",
    "papers": []
  },
  "aer": {
    "label": "AER",
    "papers": []
  },
  "health-econ": {
    "label": "Health Economics",
    "papers": [
      {
        "title": "Editorial: IZA Journal of Labor Economics",
        "authors": "Cahuc, Hotz, Gielen et al.",
        "year": "2012",
        "doi": "10.1186/2193-8997-1-1",
        "link": "https://doi.org/10.1186/2193-8997-1-1"
      },
      {
        "title": "Economic and Policy Research Interests Highlighted in the 25th NIMH-Sponsored Mental Health Services Research Conference",
        "authors": "Humensky, Freed, Azrin et al.",
        "year": "2023",
        "doi": null,
        "link": null
      },
      {
        "title": "Minimum legal drinking age and educational outcomes.",
        "authors": "Bagues, Villa",
        "year": "2025",
        "doi": "10.1016/j.jhealeco.2025.103078",
        "link": "https://doi.org/10.1016/j.jhealeco.2025.103078"
      },
      {
        "title": "Impact of Comprehensive Smoking Bans on the Health of Infants and Children",
        "authors": "McGeary, Dave, Lipton et al.",
        "year": "2017",
        "doi": "10.1086/706622",
        "link": "https://doi.org/10.1086/706622"
      },
      {
        "title": "Adis launches open-access pharmacoeconomics journal",
        "authors": "Carswell",
        "year": "2016",
        "doi": "10.1007/s40274-016-3266-z",
        "link": "https://doi.org/10.1007/s40274-016-3266-z"
      }
    ]
  },
  "qje": {
    "label": "QJE",
    "papers": []
  },
  "restat": {
    "label": "REStat",
    "papers": [
      {
        "title": "European guidance for the diagnosis and management of osteoporosis in postmenopausal women",
        "authors": "Kanis, Burlet, Cooper et al.",
        "year": "2008",
        "doi": "10.1007/s00198-008-0560-z",
        "link": "https://doi.org/10.1007/s00198-008-0560-z"
      },
      {
        "title": "Michigan Business & Entrepreneurial Law Review",
        "authors": "Social, Hansmann, Kraakman et al.",
        "year": "None",
        "doi": "10.36639/mbelr",
        "link": "https://doi.org/10.36639/mbelr"
      }
    ]
  }
}