{
  "updated_at": "2026-04-10T19:16:11.482323+00:00",
  "activities": [
    {
      "id": 18057088836,
      "name": "Afternoon Run",
      "type": "Run",
      "distance_m": 4319.9,
      "moving_time_s": 1220,
      "start_date": "2026-04-10T14:18:50Z",
      "total_elev_m": 26.0,
      "avg_speed_ms": 3.541,
      "avg_watts": null,
      "avg_hr": 160.9
    },
    {
      "id": 18040429650,
      "name": "Temphold up hills, easy down",
      "type": "Run",
      "distance_m": 5629.5,
      "moving_time_s": 1608,
      "start_date": "2026-04-09T08:19:11Z",
      "total_elev_m": 58.0,
      "avg_speed_ms": 3.501,
      "avg_watts": null,
      "avg_hr": 166.9
    },
    {
      "id": 18026631651,
      "name": "Does anyone enjoy running in NC",
      "type": "Run",
      "distance_m": 6346.2,
      "moving_time_s": 2124,
      "start_date": "2026-04-08T08:14:22Z",
      "total_elev_m": 60.0,
      "avg_speed_ms": 2.988,
      "avg_watts": null,
      "avg_hr": 145.1
    },
    {
      "id": 18026075572,
      "name": "Afternoon Walk",
      "type": "Walk",
      "distance_m": 1123.3,
      "moving_time_s": 1158,
      "start_date": "2026-04-07T17:32:26Z",
      "total_elev_m": 9.0,
      "avg_speed_ms": 0.97,
      "avg_watts": null,
      "avg_hr": 75.7
    },
    {
      "id": 17992174143,
      "name": "30 min run w mom, 30 min w sister",
      "type": "Run",
      "distance_m": 10846.9,
      "moving_time_s": 3701,
      "start_date": "2026-04-05T15:40:24Z",
      "total_elev_m": 42.0,
      "avg_speed_ms": 2.931,
      "avg_watts": null,
      "avg_hr": 144.6
    },
    {
      "id": 17987581107,
      "name": "Morning Walk",
      "type": "Walk",
      "distance_m": 3011.5,
      "moving_time_s": 2249,
      "start_date": "2026-04-05T08:28:10Z",
      "total_elev_m": 18.0,
      "avg_speed_ms": 1.339,
      "avg_watts": null,
      "avg_hr": 84.7
    },
    {
      "id": 17976396686,
      "name": "Tempo intervals w sister",
      "type": "Run",
      "distance_m": 11341.9,
      "moving_time_s": 3283,
      "start_date": "2026-04-04T09:51:37Z",
      "total_elev_m": 44.0,
      "avg_speed_ms": 3.455,
      "avg_watts": null,
      "avg_hr": 164.4
    },
    {
      "id": 17955075204,
      "name": "Run to and around campus",
      "type": "Run",
      "distance_m": 11795.0,
      "moving_time_s": 3612,
      "start_date": "2026-04-02T16:51:04Z",
      "total_elev_m": 64.0,
      "avg_speed_ms": 3.266,
      "avg_watts": null,
      "avg_hr": 161.5
    },
    {
      "id": 17938915352,
      "name": "Catch up on TTH podcast",
      "type": "Run",
      "distance_m": 11494.1,
      "moving_time_s": 3648,
      "start_date": "2026-04-01T08:45:30Z",
      "total_elev_m": 52.0,
      "avg_speed_ms": 3.151,
      "avg_watts": null,
      "avg_hr": 156.6
    },
    {
      "id": 17931983220,
      "name": "Legs didn't feel great",
      "type": "VirtualRide",
      "distance_m": 21789.3,
      "moving_time_s": 3526,
      "start_date": "2026-03-31T23:16:25Z",
      "total_elev_m": 172.0,
      "avg_speed_ms": 6.18,
      "avg_watts": 89.9,
      "avg_hr": 96.1
    },
    {
      "id": 17918666708,
      "name": "DNF - \"9 min of pain\"",
      "type": "VirtualRide",
      "distance_m": 15740.9,
      "moving_time_s": 1820,
      "start_date": "2026-03-30T23:05:08Z",
      "total_elev_m": 135.0,
      "avg_speed_ms": 8.649,
      "avg_watts": 189.7,
      "avg_hr": 128.0
    },
    {
      "id": 17912231610,
      "name": "Recovery swim",
      "type": "Swim",
      "distance_m": 845.8,
      "moving_time_s": 1803,
      "start_date": "2026-03-30T08:55:06Z",
      "total_elev_m": 0,
      "avg_speed_ms": 0.469,
      "avg_watts": null,
      "avg_hr": 129.6
    },
    {
      "id": 17906624969,
      "name": "Afternoon Walk",
      "type": "Walk",
      "distance_m": 1031.8,
      "moving_time_s": 1090,
      "start_date": "2026-03-29T17:42:57Z",
      "total_elev_m": 14.0,
      "avg_speed_ms": 0.947,
      "avg_watts": null,
      "avg_hr": 97.0
    },
    {
      "id": 17905546455,
      "name": "Lost control on the easy run",
      "type": "Run",
      "distance_m": 9094.9,
      "moving_time_s": 2490,
      "start_date": "2026-03-29T14:46:10Z",
      "total_elev_m": 33.0,
      "avg_speed_ms": 3.653,
      "avg_watts": null,
      "avg_hr": 174.2
    },
    {
      "id": 17903793519,
      "name": "Lunch Walk",
      "type": "Walk",
      "distance_m": 3142.4,
      "moving_time_s": 3111,
      "start_date": "2026-03-29T11:03:05Z",
      "total_elev_m": 37.0,
      "avg_speed_ms": 1.01,
      "avg_watts": null,
      "avg_hr": 86.6
    },
    {
      "id": 17821847979,
      "name": "Short fam walk in NC",
      "type": "Walk",
      "distance_m": 1646.9,
      "moving_time_s": 1473,
      "start_date": "2026-03-22T17:15:35Z",
      "total_elev_m": 10.0,
      "avg_speed_ms": 1.118,
      "avg_watts": null,
      "avg_hr": 84.1
    },
    {
      "id": 17800985997,
      "name": "10x2' at VT2, 1:1 jog",
      "type": "Run",
      "distance_m": 11750.6,
      "moving_time_s": 3427,
      "start_date": "2026-03-21T06:04:05Z",
      "total_elev_m": 23.0,
      "avg_speed_ms": 3.429,
      "avg_watts": null,
      "avg_hr": 154.1
    },
    {
      "id": 17794172760,
      "name": "Recovery spin /junk KMs",
      "type": "VirtualRide",
      "distance_m": 22888.3,
      "moving_time_s": 3668,
      "start_date": "2026-03-20T17:18:30Z",
      "total_elev_m": 221.0,
      "avg_speed_ms": 6.24,
      "avg_watts": 81.4,
      "avg_hr": 40.0
    },
    {
      "id": 17792495316,
      "name": "Lunch Walk",
      "type": "Walk",
      "distance_m": 2164.0,
      "moving_time_s": 1682,
      "start_date": "2026-03-20T11:22:01Z",
      "total_elev_m": 2.0,
      "avg_speed_ms": 1.287,
      "avg_watts": null,
      "avg_hr": 77.1
    },
    {
      "id": 17792495168,
      "name": "Morning Walk",
      "type": "Walk",
      "distance_m": 2370.7,
      "moving_time_s": 2199,
      "start_date": "2026-03-20T08:34:15Z",
      "total_elev_m": 24.0,
      "avg_speed_ms": 1.078,
      "avg_watts": null,
      "avg_hr": 83.5
    },
    {
      "id": 17783112920,
      "name": "Zwift - Race: Stage 5: Zwift Games: Three Step Sisters (B)",
      "type": "VirtualRide",
      "distance_m": 38174.3,
      "moving_time_s": 4047,
      "start_date": "2026-03-19T18:11:24Z",
      "total_elev_m": 589.0,
      "avg_speed_ms": 9.433,
      "avg_watts": 285.1,
      "avg_hr": 161.9
    },
    {
      "id": 17781066141,
      "name": "Family walk",
      "type": "Walk",
      "distance_m": 2001.1,
      "moving_time_s": 2161,
      "start_date": "2026-03-19T11:43:42Z",
      "total_elev_m": 17.0,
      "avg_speed_ms": 0.926,
      "avg_watts": null,
      "avg_hr": 80.4
    },
    {
      "id": 17769804497,
      "name": "\"Endurance Building Blocks\"",
      "type": "VirtualRide",
      "distance_m": 41715.2,
      "moving_time_s": 4041,
      "start_date": "2026-03-18T17:00:22Z",
      "total_elev_m": 163.0,
      "avg_speed_ms": 10.323,
      "avg_watts": 223.4,
      "avg_hr": 139.8
    },
    {
      "id": 17758404982,
      "name": "A little threshold gardening",
      "type": "Run",
      "distance_m": 6070.0,
      "moving_time_s": 1801,
      "start_date": "2026-03-17T14:54:11Z",
      "total_elev_m": 0,
      "avg_speed_ms": 3.37,
      "avg_watts": null,
      "avg_hr": 158.7
    },
    {
      "id": 17757781637,
      "name": "6-100s pretty hard",
      "type": "Swim",
      "distance_m": 1485.9,
      "moving_time_s": 1776,
      "start_date": "2026-03-17T14:13:00Z",
      "total_elev_m": 0,
      "avg_speed_ms": 0.837,
      "avg_watts": null,
      "avg_hr": 124.1
    },
    {
      "id": 17748425925,
      "name": "\"Alpha\"",
      "type": "VirtualRide",
      "distance_m": 15385.4,
      "moving_time_s": 1829,
      "start_date": "2026-03-16T23:36:05Z",
      "total_elev_m": 121.0,
      "avg_speed_ms": 8.412,
      "avg_watts": 216.1,
      "avg_hr": 113.1
    },
    {
      "id": 17746036015,
      "name": "2-300s",
      "type": "Swim",
      "distance_m": 640.1,
      "moving_time_s": 1806,
      "start_date": "2026-03-16T15:11:49Z",
      "total_elev_m": 0,
      "avg_speed_ms": 0.354,
      "avg_watts": null,
      "avg_hr": 130.1
    },
    {
      "id": 17737687630,
      "name": "Recovery spin",
      "type": "VirtualRide",
      "distance_m": 20716.1,
      "moving_time_s": 3659,
      "start_date": "2026-03-15T23:31:22Z",
      "total_elev_m": 216.0,
      "avg_speed_ms": 5.662,
      "avg_watts": 81.8,
      "avg_hr": 97.8
    },
    {
      "id": 17723563234,
      "name": "Threshold farming: 5x mile + 1' kicker",
      "type": "Run",
      "distance_m": 14165.9,
      "moving_time_s": 3848,
      "start_date": "2026-03-14T14:38:43Z",
      "total_elev_m": 34.0,
      "avg_speed_ms": 3.681,
      "avg_watts": null,
      "avg_hr": 162.4
    },
    {
      "id": 17712649389,
      "name": "Afternoon Swim",
      "type": "Swim",
      "distance_m": 2354.6,
      "moving_time_s": 3210,
      "start_date": "2026-03-13T15:56:44Z",
      "total_elev_m": 0,
      "avg_speed_ms": 0.734,
      "avg_watts": null,
      "avg_hr": 131.3
    }
  ]
}